optycode_sdk/__init__.py
optycode_sdk/client.py
optycode_sdk-1.1.1.dist-info/licenses/LICENSE
optycode_sdk-1.1.1.dist-info/METADATA
optycode_sdk-1.1.1.dist-info/WHEEL
optycode_sdk-1.1.1.dist-info/top_level.txt
optycode_sdk-1.1.1.dist-info/RECORD
